setup.py
calculate/__init__.py
calculate/adjusted_monthly_value.py
calculate/age.py
calculate/at_percentile.py
calculate/benfords_law.py
calculate/competition_rank.py
calculate/date_range.py
calculate/decile.py
calculate/elfi.py
calculate/equal_sized_breakpoints.py
calculate/margin_of_victory.py
calculate/mean.py
calculate/mean_center.py
calculate/median.py
calculate/mode.py
calculate/models.py
calculate/nudge_points.py
calculate/ordinal_rank.py
calculate/pearson.py
calculate/per_capita.py
calculate/per_sqmi.py
calculate/percentage.py
calculate/percentage_change.py
calculate/percentile.py
calculate/ptable.py
calculate/random_point.py
calculate/range.py
calculate/split_at_breakpoints.py
calculate/standard_deviation.py
calculate/standard_deviation_distance.py
calculate/summary_stats.py
calculate/tests.py
calculate/variation_coefficient.py
latimes_calculate.egg-info/PKG-INFO
latimes_calculate.egg-info/SOURCES.txt
latimes_calculate.egg-info/dependency_links.txt
latimes_calculate.egg-info/requires.txt
latimes_calculate.egg-info/top_level.txt