Metadata-Version: 1.1
Name: latimes-calculate
Version: 0.2.4
Summary: Some simple math we use to do journalism.
Home-page: http://github.com/datadesk/latimes-calculate
Author: Ben Welsh
Author-email: ben.welsh@latimes.com
License: MIT
Download-URL: http://github.com/datadesk/latimes-calculate.git
Keywords: math statistics gis geospatial numbers
Platform: UNKNOWN
Classifier: Intended Audience :: Developers
Classifier: Intended Audience :: Science/Research
Classifier: License :: OSI Approved :: MIT License
Classifier: Operating System :: OS Independent
Classifier: Programming Language :: Python
Classifier: Topic :: Software Development :: Libraries :: Python Modules
